dbis_functional_dependencies/BCNF.py
dbis_functional_dependencies/__init__.py
dbis_functional_dependencies/fdcheck.py
dbis_functional_dependencies/fds.py
dbis_functional_dependencies/fdsbase.py
dbis_functional_dependencies-1.0.2.dist-info/licenses/LICENSE
dbis_functional_dependencies-1.0.2.dist-info/METADATA
dbis_functional_dependencies-1.0.2.dist-info/WHEEL
dbis_functional_dependencies-1.0.2.dist-info/top_level.txt
dbis_functional_dependencies-1.0.2.dist-info/RECORD
